LICENSE
MANIFEST.in
README.md
setup.py
imbox/__init__.py
imbox/imap.py
imbox/parser.py
imbox/query.py
imbox/utils.py
swdt_imbox.egg-info/PKG-INFO
swdt_imbox.egg-info/SOURCES.txt
swdt_imbox.egg-info/dependency_links.txt
swdt_imbox.egg-info/not-zip-safe
swdt_imbox.egg-info/requires.txt
swdt_imbox.egg-info/top_level.txt