Metadata-Version: 1.1
Name: swdt-imbox
Version: 0.5.6
Summary: Python IMAP for Human beings. Python3 only
Home-page: https://github.com/ookami-kb/imbox
Author: Kirill Bubochkin
Author-email: ookami.kb@gmail.com
License: MIT
Keywords: email,IMAP,parsing emails
Platform: UNKNOWN
Classifier: Programming Language :: Python
Classifier: Programming Language :: Python :: 3.2
Classifier: Programming Language :: Python :: 3.3
Classifier: Programming Language :: Python :: 3.4
